craterpy/__init__.py
craterpy/classes.py
craterpy/crs.py
craterpy/helper.py
craterpy/data/craters/README.md
craterpy/data/craters/callisto_craters_km.csv
craterpy/data/craters/ceres_craters_km.csv
craterpy/data/craters/dione_craters_km.csv
craterpy/data/craters/enceladus_craters_km.csv
craterpy/data/craters/europa_craters_km.csv
craterpy/data/craters/ganymede_craters_km.csv
craterpy/data/craters/iapetus_craters_km.csv
craterpy/data/craters/mars_craters_km.csv
craterpy/data/craters/mercury_craters_km.csv
craterpy/data/craters/moon_craters_km.csv
craterpy/data/craters/pluto_craters_km.csv
craterpy/data/craters/rhea_craters_km.csv
craterpy/data/craters/tethys_craters_km.csv
craterpy/data/craters/venus_craters_km.csv
craterpy/data/craters/vesta_craters_km.csv
craterpy/data/images/README.md
craterpy/data/images/callisto.tif
craterpy/data/images/ceres.tif
craterpy/data/images/dione.tif
craterpy/data/images/earth.tif
craterpy/data/images/enceladus.tif
craterpy/data/images/europa.tif
craterpy/data/images/ganymede.tif
craterpy/data/images/iapetus.tif
craterpy/data/images/mars.tif
craterpy/data/images/mercury.tif
craterpy/data/images/moon.tif
craterpy/data/images/moon_dem.tif
craterpy/data/images/phobos.tif
craterpy/data/images/pluto.tif
craterpy/data/images/rhea.tif
craterpy/data/images/tethys.tif
craterpy/data/images/titan.tif
craterpy/data/images/venus.tif
craterpy/data/images/vesta.tif
craterpy/tests/__init__.py
craterpy/tests/test_classes.py
craterpy/tests/test_crs.py
craterpy/tests/test_helper.py
craterpy-0.10.0.dist-info/METADATA
craterpy-0.10.0.dist-info/WHEEL
craterpy-0.10.0.dist-info/licenses/LICENSE.txt
craterpy-0.10.0.dist-info/RECORD
