Metadata-Version: 2.4
Name: craterpy
Version: 0.10.0
Summary: Impact crater data science in Python.
Project-URL: Bug Tracker, https://github.com/cjtu/craterpy/issues
Project-URL: homepage, https://github.com/cjtu/craterpy
Project-URL: repository, https://github.com/cjtu/craterpy
Project-URL: documentation, https://readthedocs.org/projects/craterpy/
Author-email: "Christian J. Tai Udovicic" <cj.taiudovicic@gmail.com>
License: MIT
License-File: LICENSE.txt
Keywords: crater,data analysis,moon,planetary,python
Classifier: Development Status :: 4 - Beta
Classifier: Intended Audience :: Science/Research
Classifier: License :: OSI Approved :: MIT License
Classifier: Natural Language :: English
Classifier: Operating System :: OS Independent
Classifier: Programming Language :: Python :: 3.10
Classifier: Topic :: Scientific/Engineering :: Astronomy
Requires-Python: <4.0,>=3.10
Requires-Dist: antimeridian<1.0.0,>=0.4.0
Requires-Dist: cartopy<1.0.0,>=0.24.0
Requires-Dist: geopandas<2.0.0,>=1.0.1
Requires-Dist: joblib>=1.5.2
Requires-Dist: matplotlib<4.0.0,>=3.10.1
Requires-Dist: numpy<3.0.0,>=2.2.4
Requires-Dist: pandas<3.0.0,>=2.2.3
Requires-Dist: rasterio<2.0.0,>=1.3.10
Requires-Dist: rasterstats<1.0.0,>=0.20.0
Requires-Dist: scipy<2.0.0,>=1.13.1
Requires-Dist: tqdm>=4.67.1
